{
  "Rules": [
    {
      "SettingName": "AzEnvOk",
      "Operator": "IsEquals",
      "DataType": "Boolean",
      "Operand": true,
      "MoreInfoUrl": "https://contoso.example/isdf#azenv",
      "RemediationStrings": [
        {
          "Language": "en_US",
          "Title": "Device not in Azure Public Cloud",
          "Description": "This device type must report azEnvironment = AzurePublicCloud via IMDS. Suspected malicious device."
        }
      ]
    },
    {
      "SettingName": "TenantIdOk",
      "Operator": "IsEquals",
      "DataType": "Boolean",
      "Operand": true,
      "MoreInfoUrl": "https://contoso.example/isdf#tenant",
      "RemediationStrings": [
        {
          "Language": "en_US",
          "Title": "Wrong Microsoft tenant detected",
          "Description": "IMDS tag 'tenantid' does not match corporate tenant. Suspected malicious device"
        }
      ]
    },
    {
      "SettingName": "SystemManufacturerOk",
      "Operator": "IsEquals",
      "DataType": "Boolean",
      "Operand": true,
      "MoreInfoUrl": "https://contoso.example/isdf#manufacturer",
      "RemediationStrings": [
        {
          "Language": "en_US",
          "Title": "Unexpected device attributes",
          "Description": "Suspected device tampering to bypass security controls."
        }
      ]
    },
    {
      "SettingName": "SystemProductNamePrefixOk",
      "Operator": "IsEquals",
      "DataType": "Boolean",
      "Operand": true,
      "MoreInfoUrl": "https://contoso.example/isdf#productname",
      "RemediationStrings": [
        {
          "Language": "en_US",
          "Title": "Unexpected device attributes",
          "Description": "Suspected device tampering to bypass security controls."
        }
      ]
    },
    {
      "SettingName": "HostnameMatchesProvisioned",
      "Operator": "IsEquals",
      "DataType": "Boolean",
      "Operand": true,
      "MoreInfoUrl": "https://contoso.example/isdf#hostname",
      "RemediationStrings": [
        {
          "Language": "en_US",
          "Title": "Hostname mismatch detected",
          "Description": "Current hostname does not match the IMDS-provisioned hostname. Device may have been tampered with."
        }
      ]
    }
  ],
  "Operator": "AND"
}